8int-sum/8int-sum.v
module wallace_tree_sum
   #(	parameter DATA_WIDTH = 256,
	parameter OUTPUT_WIDTH = 32,
	parameter NUM = 8)
   (input clk,
    input rst_n,
    input valid_in,
    input [DATA_WIDTH-1:0] data_in, // 8 integers * 32-bit each
    output reg valid_out,
    output reg [OUTPUT_WIDTH-1:0] sum_out  // Output sum (extra bits for overflow)
);

    // Stage 1: Pairwise sums (reducing 8 inputs to 4)
    reg [OUTPUT_WIDTH-1:0] sum_stage1 [3:0]; // Array of registers
    reg v_stage1;

    // Stage 2: Pairwise sums (reducing 4 inputs to 2)
    reg [OUTPUT_WIDTH-1:0] sum_stage2 [1:0];
    reg v_stage2;

    // Stage 3: Final sum (reducing 2 inputs to 1)
    reg [OUTPUT_WIDTH-1:0] final_sum;
    reg v_final;

    // Stage 1: Add 8 integers into 4 partial sums
    always @(posedge clk or negedge rst_n) begin
        if (!rst_n) begin
            sum_stage1[0] <= 0;
            sum_stage1[1] <= 0;
            sum_stage1[2] <= 0;
            sum_stage1[3] <= 0;
            v_stage1 <= 0;
        end else if (valid_in) begin
            sum_stage1[0] <= data_in[ 31:  0] + data_in[ 63: 32];
            sum_stage1[1] <= data_in[ 95: 64] + data_in[127: 96];
            sum_stage1[2] <= data_in[159:128] + data_in[191:160];
            sum_stage1[3] <= data_in[223:192] + data_in[255:224];
            v_stage1 <= 1;
        end else begin
            v_stage1 <= 0;
        end
    end

    // Stage 2: Add 4 partial sums into 2 sums
    always @(posedge clk or negedge rst_n) begin
        if (!rst_n) begin
            sum_stage2[0] <= 0;
            sum_stage2[1] <= 0;
            v_stage2 <= 0;
        end else if (v_stage1) begin
            sum_stage2[0] <= sum_stage1[0] + sum_stage1[1];
            sum_stage2[1] <= sum_stage1[2] + sum_stage1[3];
            v_stage2 <= 1;
        end else begin
            v_stage2 <= 0;
        end
    end

    // Stage 3: Final sum (reducing 2 numbers to 1)
    always @(posedge clk or negedge rst_n) begin
        if (!rst_n) begin
            final_sum <= 0;
            v_final <= 0;
        end else if (v_stage2) begin
            final_sum <= sum_stage2[0] + sum_stage2[1];
            v_final <= 1;
        end else begin
            v_final <= 0;
        end
    end

    // Output assignments
    always @(posedge clk) begin
        valid_out <= v_final;
        sum_out <= final_sum;
    end

    always @(posedge clk) begin
    	$display("Stage 1: %d %d %d %d", sum_stage1[0], sum_stage1[1], sum_stage1[2], sum_stage1[3]);
    	$display("Stage 2: %d %d", sum_stage2[0], sum_stage2[1]);
    	$display("Final Sum: %d", final_sum);
    end


endmodule

8int-sum/8int-sum_tb.v
`timescale 1ns/1ps

module wallace_tree_sum_tb;

    reg clk;
    reg rst_n;
    reg valid_in;
    reg [255:0] data_in;
    wire valid_out;
    wire [31:0] sum_out;

    // Instantiate the DUT (Device Under Test)
    wallace_tree_sum uut (
        .clk(clk),
        .rst_n(rst_n),
        .valid_in(valid_in),
        .data_in(data_in),
        .valid_out(valid_out),
        .sum_out(sum_out)
    );

    // Generate clock
    always #5 clk = ~clk;  // 10 ns period

    // Test sequence
    initial begin
        $dumpfile("wave.vcd");  // Generate VCD file for waveform analysis
        $dumpvars(0, wallace_tree_sum_tb);
	$dumpvars(1, uut);

        clk = 0;
        rst_n = 0;
        valid_in = 0;
        data_in = 0;

        // Reset
        #10 rst_n = 1;

        // Apply test vector
        #10 valid_in = 1;
            data_in = {32'h00000001, 32'h00000002, 32'h00000003, 32'h00000004, 
                       32'h00000005, 32'h00000006, 32'h00000007, 32'h00000008}; // Expected sum = 36

        #10 valid_in = 0; // Wait for result

        #50 $finish;
    end

endmodule

8int-sum/wave.vcd
$date
	Fri Feb 21 12:53:38 2025
$end
$version
	Icarus Verilog
$end
$timescale
	1ps
$end
$scope module wallace_tree_sum_tb $end
$var wire 1 ! valid_out $end
$var wire 32 " sum_out [31:0] $end
$var reg 1 # clk $end
$var reg 256 $ data_in [255:0] $end
$var reg 1 % rst_n $end
$var reg 1 & valid_in $end
$scope module uut $end
$var wire 1 # clk $end
$var wire 256 ' data_in [255:0] $end
$var wire 1 % rst_n $end
$var wire 1 & valid_in $end
$var reg 32 ( final_sum [31:0] $end
$var reg 32 ) sum_out [31:0] $end
$var reg 1 * v_final $end
$var reg 1 + v_stage1 $end
$var reg 1 , v_stage2 $end
$var reg 1 ! valid_out $end
$upscope $end
$upscope $end
$scope module wallace_tree_sum_tb $end
$scope module uut $end
$upscope $end
$upscope $end
$enddefinitions $end
#0
$dumpvars
0,
0+
0*
bx )
b0 (
b0 '
0&
0%
b0 $
0#
bx "
x!
$end
#5000
b0 "
b0 )
0!
1#
#10000
0#
1%
#15000
1#
#20000
0#
b100000000000000000000000000000010000000000000000000000000000000110000000000000000000000000000010000000000000000000000000000000101000000000000000000000000000001100000000000000000000000000000011100000000000000000000000000001000 $
b100000000000000000000000000000010000000000000000000000000000000110000000000000000000000000000010000000000000000000000000000000101000000000000000000000000000001100000000000000000000000000000011100000000000000000000000000001000 '
1&
#25000
1+
1#
#30000
0#
0&
#35000
0+
1,
1#
#40000
0#
#45000
1*
b100100 (
0,
1#
#50000
0#
#55000
b100100 "
b100100 )
1!
0*
1#
#60000
0#
#65000
0!
1#
