8int-sum_iob-cache/constants.vh
`define ADDR_BUS_W 24
`define FE_ADDR_W 22
`define FE_DATA_W 32
`define BE_DATA_W 64
`define BE_ADDR_W 24
`define BE_STRB_W 8
`define FE_STRB_W 4

vector_ram/vec_ram.v
`include "constants.vh"

module vec_ram (
    input                        clk_i,
    input                        en_i,
    input       [`BE_STRB_W-1 :0] we_i,   // 8-bit write enable (1 bit per byte)
    input       [`BE_ADDR_W-1 :0] addr_i, // 24-bit address, only lower 15 bits used
    input       [`BE_DATA_W-1 :0] d_i,    // 64-bit input data (8 bytes)
    output reg  [`BE_DATA_W-1 :0] d_o     // 64-bit output data (8 bytes)
);

    // Memory: 32768 bytes total
    reg [`BE_STRB_W-1 :0] mem [0:32767]; 

    wire [14:0] byte_addr = addr_i[14:0]; // Use lower 15 bits for addressing

    integer i;

    always @(posedge clk_i) begin
        if (en_i) begin
            // Write operation
            for (i = 0; i < 8; i = i + 1) begin
                if (we_i[7 - i]) 
                    mem[byte_addr + i] <= d_i[((8-i)*8-1) -: 8];
            end
            // Read operation
            d_o <= {mem[byte_addr+0], mem[byte_addr+1], mem[byte_addr+2], mem[byte_addr+3],
                    mem[byte_addr+4], mem[byte_addr+5], mem[byte_addr+6], mem[byte_addr+7]};
        end
    end

endmodule

vector_ram/vec_ram_tb.v
`timescale 1ns/1ps

`include "constants.vh"

module tb_native_ram;

    // Signals
    reg clk_i;
    reg en_i;
    reg [`BE_STRB_W-1 :0] we_i;     // 8-bit write enable
    reg [`BE_ADDR_W-1 :0] addr_i;  // 24-bit address
    reg [`BE_DATA_W-1 :0] d_i;     // 64-bit input data
    wire [`BE_DATA_W-1 :0] d_o;    // 64-bit output data

    // Instantiate RAM
    vec_ram uut (
        .clk_i(clk_i),
        .en_i(en_i),
        .we_i(we_i),
        .addr_i(addr_i),
        .d_i(d_i),
        .d_o(d_o)
    );

    // Clock generation
    always #5 clk_i = ~clk_i; // 10ns clock period (100MHz)

    // Test procedure
    initial begin
        $dumpfile("wave_ram.vcd"); // Set the VCD file name
        $dumpvars(0, tb_native_ram); // Dump all signals in the testbench

        // Initialize signals
        clk_i = 0;
        en_i  = 0;
        we_i  = 0;
        addr_i = 0;
        d_i = 0;

        #10; // Wait some cycles

        // Enable memory operations
        en_i = 1;

        // Test Case 1: Full-word write to address 0
        addr_i = 24'h000000;
        d_i = 64'h1122334455667788;
        we_i = 8'hFF; // Enable all 8 bytes
        #10;
        we_i = 8'h00;
        #10;
        $display("Read from addr 0: %h", d_o);
        if (d_o !== 64'h1122334455667788)
            $display("ERROR: Full word read mismatch at addr 0");

        // Test Case 2: Partial write to address 4
        addr_i = 24'h000004;
        d_i = 64'hAABBCCDDEEFF0011;
        we_i = 8'h0F; // Enable lower 4 bytes
        #10;
        we_i = 8'h00;
        #10;
        $display("Read from addr 4: %h", d_o);
        if (d_o[31:0] !== 32'hEEFF0011)
            $display("ERROR: Partial write mismatch at addr 4");

        // Test Case 3: Full-word write to address 8
        addr_i = 24'h000008;
        d_i = 64'h2233445566778899;
        we_i = 8'hFF;
        #10;
        we_i = 8'h00;
        #10;
        $display("Read from addr 8: %h", d_o);
        if (d_o !== 64'h2233445566778899)
            $display("ERROR: Full word read mismatch at addr 8");

        // Test Case 4: Overlapping read from address 2
        addr_i = 24'h000002;
        #10;
        $display("Read from addr 2: %h", d_o);
        if (d_o !== 64'h8899EEFF00115566)
            $display("ERROR: Overlapping read mismatch at addr 2");

        $display("Test completed successfully.");
        $finish;
    end

endmodule

8int-sum_iob-cache/wave_ram.vcd
$date
	Mon May  5 22:50:00 2025
$end
$version
	Icarus Verilog
$end
$timescale
	1ps
$end
$scope module tb_native_ram $end
$var wire 64 ! d_o [63:0] $end
$var reg 24 " addr_i [23:0] $end
$var reg 1 # clk_i $end
$var reg 64 $ d_i [63:0] $end
$var reg 1 % en_i $end
$var reg 8 & we_i [7:0] $end
$scope module uut $end
$var wire 24 ' addr_i [23:0] $end
$var wire 1 # clk_i $end
$var wire 64 ( d_i [63:0] $end
$var wire 1 % en_i $end
$var wire 8 ) we_i [7:0] $end
$var wire 15 * byte_addr [14:0] $end
$var reg 64 + d_o [63:0] $end
$var integer 32 , i [31:0] $end
$upscope $end
$upscope $end
$enddefinitions $end
#0
$dumpvars
bx ,
bx +
b0 *
b0 )
b0 (
b0 '
b0 &
0%
b0 $
0#
b0 "
bx !
$end
#5000
1#
#10000
0#
b11111111 &
b11111111 )
b1000100100010001100110100010001010101011001100111011110001000 $
b1000100100010001100110100010001010101011001100111011110001000 (
1%
#15000
b1000 ,
1#
#20000
0#
b0 &
b0 )
#25000
b1000100100010001100110100010001010101011001100111011110001000 !
b1000100100010001100110100010001010101011001100111011110001000 +
b1000 ,
1#
#30000
b100 *
0#
b1111 &
b1111 )
b1010101010111011110011001101110111101110111111110000000000010001 $
b1010101010111011110011001101110111101110111111110000000000010001 (
b100 "
b100 '
#35000
b1010101011001100111011110001000xxxxxxxxxxxxxxxxxxxxxxxxxxxxxxxx !
b1010101011001100111011110001000xxxxxxxxxxxxxxxxxxxxxxxxxxxxxxxx +
b1000 ,
1#
#40000
0#
b0 &
b0 )
#45000
b101010101100110011101111000100011101110111111110000000000010001 !
b101010101100110011101111000100011101110111111110000000000010001 +
b1000 ,
1#
#50000
b1000 *
0#
b11111111 &
b11111111 )
b10001000110011010001000101010101100110011101111000100010011001 $
b10001000110011010001000101010101100110011101111000100010011001 (
b1000 "
b1000 '
#55000
b11101110111111110000000000010001xxxxxxxxxxxxxxxxxxxxxxxxxxxxxxxx !
b11101110111111110000000000010001xxxxxxxxxxxxxxxxxxxxxxxxxxxxxxxx +
b1000 ,
1#
#60000
0#
b0 &
b0 )
#65000
b10001000110011010001000101010101100110011101111000100010011001 !
b10001000110011010001000101010101100110011101111000100010011001 +
b1000 ,
1#
#70000
b10 *
0#
b10 "
b10 '
#75000
b11001101000100010101010110011001110111100010000010001000110011 !
b11001101000100010101010110011001110111100010000010001000110011 +
b1000 ,
1#
