8int-sum_iob-cache/constants.vh
`define ADDR_BUS_W 24
`define FE_ADDR_W 22
`define FE_DATA_W 32
`define BE_DATA_W 64
`define BE_ADDR_W 24
`define BE_STRB_W 8
`define FE_STRB_W 4

8int-sum/8int-sum_v2.v
`include "constants.vh"

module int_sum_v2
    (
        // Clock and reset
        input clk,
        input rst_n,

        // Interface to bus_controller
        output reg acc_valid,              // Request valid
        output reg [`FE_ADDR_W-1 :0] acc_addr,        // Address for read/write
        output reg [`FE_DATA_W-1 :0] acc_wdata,      // Write data
        output reg [`FE_STRB_W-1 :0] acc_wstrb,       // Write strobe
        input wire [`FE_DATA_W-1 :0] acc_rdata,      // Read data
        input wire acc_rvalid,             // Read data valid
        input wire acc_ready,              // Request accepted

        // Control signals (memory-mapped registers)
        input wire start,                  // Start computation
        input wire [`FE_ADDR_W-1 :0] input_addr,      // Input data starting address
        input wire [`FE_ADDR_W-1 :0] output_addr,     // Output data starting address
        input wire [31:0] N,               // Number of 256-bit blocks
        output reg done                    // Computation complete
    );

    // Internal registers
    reg [`FE_DATA_W-1 :0] input_buffer [0:3];        // Buffer for input data
    reg [31:0] output_buffer [0:3];        // Buffer for output sums
    reg [1:0] input_head, input_tail;      // Buffer pointers
    reg [1:0] output_head, output_tail;
    reg [31:0] count;                      // Processed block counter
    reg [`FE_ADDR_W-1 :0] current_input_addr;         // Current read address
    reg [`FE_ADDR_W-1 :0] current_output_addr;        // Current write address

    // Pipeline registers
    reg [OUTPUT_WIDTH-1:0] sum_stage1 [3:0]; // Stage 1: 8 -> 4
    reg v_stage1;
    reg [OUTPUT_WIDTH-1:0] sum_stage2 [1:0]; // Stage 2: 4 -> 2
    reg v_stage2;
    reg [OUTPUT_WIDTH-1:0] final_sum;        // Stage 3: 2 -> 1
    reg v_final;

    // State machine
    reg [2:0] state;
    localparam IDLE = 0,
               READ_REQUEST = 1,
               WAIT_FOR_DATA = 2,
               PROCESS = 3,
               WRITE_REQUEST = 4,
               WAIT_FOR_WRITE = 5,
               DONE = 6;

    // Main FSM and logic
    always @(posedge clk or negedge rst_n) begin
        if (!rst_n) begin
            state <= IDLE;
            acc_valid <= 0;
            done <= 0;
            count <= 0;
            input_head <= 0;
            input_tail <= 0;
            output_head <= 0;
            output_tail <= 0;
            current_input_addr <= 0;
            current_output_addr <= 0;
            v_stage1 <= 0;
            v_stage2 <= 0;
            v_final <= 0;
        end else begin
            case (state)
                IDLE: begin
                    if (start) begin
                        state <= READ_REQUEST;
                        current_input_addr <= input_addr;
                        current_output_addr <= output_addr;
                        count <= 0;
                    end
                end

                READ_REQUEST: begin
                    // Request data if buffer not full and more data needed
                    if (count < N && (input_head - input_tail) < 4) begin
                        acc_valid <= 1;
                        acc_addr <= current_input_addr;
                        acc_wstrb <= 32'h0; // Read request (no write)
                        if (acc_ready) begin
                            acc_valid <= 0;
                            current_input_addr <= current_input_addr + 1;
                            state <= WAIT_FOR_DATA;
                        end
                    end else begin
                        state <= PROCESS;
                    end
                end

                WAIT_FOR_DATA: begin
                    if (acc_rvalid) begin
                        input_buffer[input_tail] <= acc_rdata;
                        input_tail <= input_tail + 1;
                        state <= READ_REQUEST;
                    end
                end

                PROCESS: begin
                    // Issue write request if output buffer has data and no request is pending
                    if (output_head != output_tail && !acc_valid) begin
                        acc_valid <= 1;
                        acc_addr <= current_output_addr;
                        acc_wdata <= {224'b0, output_buffer[output_head]}; // 32-bit result, padded to 256 bits
                        acc_wstrb <= 32'h0000000F; // Write 32 bits
                    end
                    // Issue read request if input buffer has space, more data needed, and no request pending
                    else if ((input_head - input_tail) < 4 && count < N && !acc_valid) begin
                        acc_valid <= 1;
                        acc_addr <= current_input_addr;
                        acc_wstrb <= 32'h00000000; // Read request
                    end

                    // Handle request acceptance
                    if (acc_valid && acc_ready) begin
                        acc_valid <= 0;
                        if (acc_wstrb != 0) begin // Write accepted
                            output_head <= output_head + 1;
                            current_output_addr <= current_output_addr + 1;
                        end else begin // Read accepted
                            current_input_addr <= current_input_addr + 1;
                        end
                    end

                    // Store incoming read data
                    if (acc_rvalid) begin
                        input_buffer[input_tail] <= acc_rdata;
                        input_tail <= input_tail + 1;
                    end

                    // Feed pipeline if data available
                    if (input_head != input_tail) begin
                        sum_stage1[0] <= input_buffer[input_head][31:0] + input_buffer[input_head][63:32];
                        sum_stage1[1] <= input_buffer[input_head][95:64] + input_buffer[input_head][127:96];
                        sum_stage1[2] <= input_buffer[input_head][159:128] + input_buffer[input_head][191:160];
                        sum_stage1[3] <= input_buffer[input_head][223:192] + input_buffer[input_head][255:224];
                        v_stage1 <= 1;
                        input_head <= input_head + 1;
                    end else begin
                        v_stage1 <= 0;
                    end

                    // Pipeline stage 2
                    if (v_stage1) begin
                        sum_stage2[0] <= sum_stage1[0] + sum_stage1[1];
                        sum_stage2[1] <= sum_stage1[2] + sum_stage1[3];
                        v_stage2 <= 1;
                    end else begin
                        v_stage2 <= 0;
                    end

                    // Pipeline stage 3
                    if (v_stage2) begin
                        final_sum <= sum_stage2[0] + sum_stage2[1];
                        v_final <= 1;
                    end else begin
                        v_final <= 0;
                    end

                    // Store result in output buffer
                    if (v_final) begin
                        output_buffer[output_tail] <= final_sum;
                        output_tail <= output_tail + 1;
                        count <= count + 1;
                    end

                    // Transition to DONE when complete
                    if (count == N && output_head == output_tail) begin
                        state <= DONE;
                    end
                end

                WAIT_FOR_WRITE: begin
                    // Optional state if write latency needs handling
                    state <= PROCESS;
                end

                DONE: begin
                    done <= 1;
                    state <= IDLE;
                end
            endcase
        end
    end

    // Pipeline Stage 2 (unchanged logic)
    always @(posedge clk or negedge rst_n) begin
        if (!rst_n) begin
            sum_stage2[0] <= 0;
            sum_stage2[1] <= 0;
            v_stage2 <= 0;
        end else if (v_stage1) begin
            sum_stage2[0] <= sum_stage1[0] + sum_stage1[1];
            sum_stage2[1] <= sum_stage1[2] + sum_stage1[3];
            v_stage2 <= 1;
        end else begin
            v_stage2 <= 0;
        end
    end

    // Remove original output assignments since sum_out is now buffered
    // Debugging statements (optional)
    always @(posedge clk) begin
        //$display("State: %d, Count: %d", state, count);
        // $display("Stage 1: %d %d %d %d", sum_stage1[0], sum_stage1[1], sum_stage1[2], sum_stage1[3]);
        // $display("Stage 2: %d %d", sum_stage2[0], sum_stage2[1]);
        // $display("Final Sum: %d", final_sum);
    end

endmodule

8int-sum/8int-sum_v2_tb.v
`include "constants.vh"

module tb_wallace_tree_sum;

    // Clock and reset
    reg clk;
    reg rst_n;

    // Interface to bus_controller
    wire acc_valid;
    wire [`FE_ADDR_W-1:0] acc_addr;        // Address bus (byte addresses for 32-bit words)
    wire [`FE_DATA_W-1:0] acc_wdata;       // Write data
    wire [`FE_STRB_W-1:0] acc_wstrb;       // Write strobe (byte enables)
    reg  [`FE_DATA_W-1:0] acc_rdata;       // Read data
    reg  acc_rvalid;                       // Read valid
    reg  acc_ready;                        // Bus ready

    // Control signals
    reg  start;
    reg  [`FE_ADDR_W-1:0] input_addr;      // Starting byte address for input data
    reg  [`FE_ADDR_W-1:0] output_addr;     // Starting byte address for output data
    reg  [31:0] N;                         // Number of blocks to process
    wire done;                             // Completion signal

    // Memory model (32-bit wide, 1024 locations = 4 KB)
    reg  [31:0] memory [0:1023];

    // Instantiate the accelerator
    int_sum_v2 dut (
        .clk(clk),
        .rst_n(rst_n),
        .acc_valid(acc_valid),
        .acc_addr(acc_addr),
        .acc_wdata(acc_wdata),
        .acc_wstrb(acc_wstrb),
        .acc_rdata(acc_rdata),
        .acc_rvalid(acc_rvalid),
        .acc_ready(acc_ready),
        .start(start),
        .input_addr(input_addr),
        .output_addr(output_addr),
        .N(N),
        .done(done)
    );

    initial begin
        $dumpfile("wave_out_acc.vcd"); // Set the VCD file name
        $dumpvars(0, tb_wallace_tree_sum); // Dump all signals in the testbench
    end

    // Clock generation: 10ns period (5ns high, 5ns low)
    always #5 clk = ~clk;

    // Memory controller logic
    reg [`FE_ADDR_W-1:0] read_addr;        // Stores address of pending read
    reg read_pending;                      // Indicates a read is in progress
    reg [1:0] read_delay;                  // Delay counter for read response

    always @(posedge clk or negedge rst_n) begin
        if (!rst_n) begin
            acc_ready <= 0;
            acc_rvalid <= 0;
            acc_rdata <= 0;
            read_pending <= 0;
            read_delay <= 0;
        end else begin
            // Default values
            acc_ready <= 0;
            acc_rvalid <= 0;

            // Handle read requests
            if (acc_valid && acc_wstrb == 0 && !read_pending) begin
                acc_ready <= 1;            // Accept the read request
                read_addr <= acc_addr;     // Store the requested byte address
                read_pending <= 1;         // Mark read as pending
                read_delay <= 2;           // Set 2-cycle delay for response
            end

            // Handle read response
            if (read_pending) begin
                if (read_delay == 0) begin
                    acc_rdata <= memory[read_addr >> 2]; // Read 32-bit word (byte addr / 4)
                    acc_rvalid <= 1;                     // Signal valid data
                    read_pending <= 0;                   // Clear pending flag
                end else begin
                    read_delay <= read_delay - 1;        // Decrement delay
                end
            end

            // Handle write requests
            if (acc_valid && acc_wstrb != 0) begin
                acc_ready <= 1;            // Accept the write immediately
                if (acc_wstrb == 4'hF) begin
                    memory[acc_addr >> 2] <= acc_wdata; // Write full 32-bit word
                end else begin
                    // Byte-wise write based on strobe
                    if (acc_wstrb[0]) memory[acc_addr >> 2][7:0]   <= acc_wdata[7:0];
                    if (acc_wstrb[1]) memory[acc_addr >> 2][15:8]  <= acc_wdata[15:8];
                    if (acc_wstrb[2]) memory[acc_addr >> 2][23:16] <= acc_wdata[23:16];
                    if (acc_wstrb[3]) memory[acc_addr >> 2][31:24] <= acc_wdata[31:24];
                end
            end
        end
    end

    // Test procedure
    initial begin
        // Initialize memory with test data (2 blocks of 8 32-bit integers each)
        memory[0]  = 32'h00000000; // Block 1: 0
        memory[1]  = 32'h00000001; // 1
        memory[2]  = 32'h00000002; // 2
        memory[3]  = 32'h00000003; // 3
        memory[4]  = 32'h00000004; // 4
        memory[5]  = 32'h00000005; // 5
        memory[6]  = 32'h00000006; // 6
        memory[7]  = 32'h00000007; // 7
        memory[8]  = 32'h00000008; // Block 2: 8
        memory[9]  = 32'h00000009; // 9
        memory[10] = 32'h0000000A; // 10
        memory[11] = 32'h0000000B; // 11
        memory[12] = 32'h0000000C; // 12
        memory[13] = 32'h0000000D; // 13
        memory[14] = 32'h0000000E; // 14
        memory[15] = 32'h0000000F; // 15
        memory[64] = 32'h00000000; // Output location 1 (byte addr 0x100)
        memory[65] = 32'h00000000; // Output location 2 (byte addr 0x104)

        // Initialize signals
        clk = 0;
        rst_n = 0;
        start = 0;
        input_addr = 22'h000000;  // Input starts at byte address 0x000000
        output_addr = 22'h000100; // Output starts at byte address 0x000100 (word addr 64)
        N = 32'd2;                // Process 2 blocks

        // Apply reset
        #10 rst_n = 1;

        // Start the accelerator
        #10 start = 1;
        #10 start = 0;            // Pulse start for one cycle

        // Wait for completion
        wait(done == 1);
        #10;                      // Allow time for final writes

        // Verify results
        if (memory[64] == 32'd28 && memory[65] == 32'd92) begin
            $display("Test passed!");
        end else begin
            $display("Test failed!");
            $display("memory[64] = %h, expected 0000001C", memory[64]);
            $display("memory[65] = %h, expected 0000005C", memory[65]);
        end

        $finish;                  // End simulation
    end

    // Debugging output
    always @(posedge clk) begin
        if (acc_valid && acc_ready) begin
            if (acc_wstrb == 0) begin
                $display("Time %t: Read request issued, addr=%h", $time, acc_addr);
            end else begin
                $display("Time %t: Write request issued, addr=%h, data=%h, wstrb=%h", 
                         $time, acc_addr, acc_wdata, acc_wstrb);
            end
        end
        if (acc_rvalid) begin
            $display("Time %t: Read response provided, data=%h", $time, acc_rdata);
        end
    end

endmodule

8int-sum_iob-cache/wave_out_acc.vcd
$date
	Fri Mar 21 09:41:05 2025
$end
$version
	Icarus Verilog
$end
$timescale
	1s
$end
$scope module tb_wallace_tree_sum $end
$var wire 1 ! done $end
$var wire 32 " acc_wstrb [31:0] $end
$var wire 256 # acc_wdata [255:0] $end
$var wire 1 $ acc_valid $end
$var wire 19 % acc_addr [18:0] $end
$var reg 32 & N [31:0] $end
$var reg 256 ' acc_rdata [255:0] $end
$var reg 1 ( acc_ready $end
$var reg 1 ) acc_rvalid $end
$var reg 1 * clk $end
$var reg 19 + input_addr [18:0] $end
$var reg 19 , output_addr [18:0] $end
$var reg 19 - read_addr [18:0] $end
$var reg 2 . read_delay [1:0] $end
$var reg 1 / read_pending $end
$var reg 1 0 rst_n $end
$var reg 1 1 start $end
$scope module dut $end
$var wire 32 2 N [31:0] $end
$var wire 256 3 acc_rdata [255:0] $end
$var wire 1 ( acc_ready $end
$var wire 1 ) acc_rvalid $end
$var wire 1 * clk $end
$var wire 19 4 input_addr [18:0] $end
$var wire 19 5 output_addr [18:0] $end
$var wire 1 0 rst_n $end
$var wire 1 1 start $end
$var reg 19 6 acc_addr [18:0] $end
$var reg 1 $ acc_valid $end
$var reg 256 7 acc_wdata [255:0] $end
$var reg 32 8 acc_wstrb [31:0] $end
$var reg 32 9 count [31:0] $end
$var reg 19 : current_input_addr [18:0] $end
$var reg 19 ; current_output_addr [18:0] $end
$var reg 1 ! done $end
$var reg 32 < final_sum [31:0] $end
$var reg 2 = input_head [1:0] $end
$var reg 2 > input_tail [1:0] $end
$var reg 2 ? output_head [1:0] $end
$var reg 2 @ output_tail [1:0] $end
$var reg 3 A state [2:0] $end
$var reg 1 B v_final $end
$var reg 1 C v_stage1 $end
$var reg 1 D v_stage2 $end
$upscope $end
$upscope $end
$enddefinitions $end
#0
$dumpvars
0D
0C
0B
b0 A
b0 @
b0 ?
b0 >
b0 =
bx <
b0 ;
b0 :
b0 9
bx 8
bx 7
bx 6
b10000 5
b0 4
b0 3
b10 2
01
00
0/
b0 .
bx -
b10000 ,
b0 +
0*
0)
0(
b0 '
b10 &
bx %
0$
bx #
bx "
0!
$end
#5
1*
#10
0*
10
#15
1*
#20
0*
11
#25
b10000 ;
b1 A
1*
#30
0*
01
#35
b0 "
b0 8
b0 %
b0 6
1$
1*
#40
0*
#45
b10 .
1/
b0 -
1(
1*
#50
0*
#55
b10 A
b1 :
0$
b1 .
0(
1*
#60
0*
#65
b0 .
1*
#70
0*
#75
0/
1)
b11100000000000000000000000000000110000000000000000000000000000001010000000000000000000000000000010000000000000000000000000000000011000000000000000000000000000000100000000000000000000000000000000100000000000000000000000000000000 '
b11100000000000000000000000000000110000000000000000000000000000001010000000000000000000000000000010000000000000000000000000000000011000000000000000000000000000000100000000000000000000000000000000100000000000000000000000000000000 3
1*
#80
0*
#85
0)
b1 A
b1 >
1*
#90
0*
#95
b11 A
1*
#100
0*
#105
b1 =
1C
1*
#110
0*
#115
0C
b1 %
b1 6
1$
1D
1*
#120
0*
#125
b10 .
1/
b1 -
1(
1B
b11100 <
0D
1*
#130
0*
#135
b1 9
b1 @
0B
b10 :
0$
b1 .
0(
1*
#140
0*
#145
b0 .
b1111 "
b1111 8
b11100 #
b11100 7
b10000 %
b10000 6
1$
1*
#150
0*
#155
1(
0/
1)
b111100000000000000000000000000001110000000000000000000000000000011010000000000000000000000000000110000000000000000000000000000001011000000000000000000000000000010100000000000000000000000000000100100000000000000000000000000001000 '
b111100000000000000000000000000001110000000000000000000000000000011010000000000000000000000000000110000000000000000000000000000001011000000000000000000000000000010100000000000000000000000000000100100000000000000000000000000001000 3
1*
#160
0*
#165
0)
1(
b10 >
b10001 ;
b1 ?
0$
1*
#170
0*
#175
b10 =
1C
0(
1*
#180
0*
#185
1D
0C
b0 "
b0 8
b10 %
b10 6
1$
1*
#190
0*
#195
1B
b1011100 <
0D
b10 .
1/
b10 -
1(
1*
#200
0*
#205
b1 .
0(
b10 9
b10 @
0B
b11 :
0$
1*
#210
0*
#215
b1111 "
b1111 8
b1011100 #
b1011100 7
b10001 %
b10001 6
1$
b0 .
1*
#220
0*
#225
1(
0/
1)
bx '
bx 3
1*
#230
0*
#235
b11 >
b10010 ;
b10 ?
0$
0)
1(
1*
#240
0*
#245
0(
b110 A
b11 =
1C
1*
#250
0*
#255
b0 A
1!
1D
1*
